kolibri_report/__init__.py
kolibri_report/report.py
kolibri_report-0.1.6.dist-info/LICENSE
kolibri_report-0.1.6.dist-info/METADATA
kolibri_report-0.1.6.dist-info/WHEEL
kolibri_report-0.1.6.dist-info/top_level.txt
kolibri_report-0.1.6.dist-info/RECORD
