Metadata-Version: 2.1
Name: kolibri-report
Version: 0.1.6
Summary: A report package for kolibri-ml
Home-page: https://github.com/Aneruth/kolibri-report
Author: Aneruth,Mohamed Ben Haddou
Author-email: ane1998@gmail.com,mbenhaddou@mentis.io
License: UNKNOWN
Project-URL: Bug Tracker, https://github.com/Aneruth/kolibri-report/issues
Platform: UNKNOWN
Classifier: Programming Language :: Python :: 3.7
Classifier: Operating System :: OS Independent
Classifier: Development Status :: 1 - Planning
Classifier: Intended Audience :: Developers
Requires-Python: >=3.7
License-File: LICENSE
Requires-Dist: kolibri-ml
Requires-Dist: seaborn
